LICENSE
README.md
setup.py
src/lunardb/__init__.py
src/lunardb/client.py
src/lunardb/exceptions.py
src/lunardb/utils.py
src/lunardb_py.egg-info/PKG-INFO
src/lunardb_py.egg-info/SOURCES.txt
src/lunardb_py.egg-info/dependency_links.txt
src/lunardb_py.egg-info/requires.txt
src/lunardb_py.egg-info/top_level.txt